_disptools.so
disptools-0.4.1.dist-info/LICENSE
disptools-0.4.1.dist-info/METADATA
disptools-0.4.1.dist-info/top_level.txt
disptools-0.4.1.dist-info/RECORD
disptools-0.4.1.dist-info/WHEEL
disptools.libs/libgomp-a34b3233.so.1.0.0
disptools/predict.py
disptools/drawing.py
disptools/displacements.py
disptools/__init__.py
disptools/io.py
disptools/simulatrophy.py
disptools/measure.py
