Metadata-Version: 2.1
Name: disptools
Version: 0.4.1
Summary: Generate displacement fields with known volume changes
Home-page: https://github.com/m-pilia/disptools
Download-URL: https://github.com/m-pilia/disptools/archive/v0.4.1.tar.gz
Author: Martino Pilia
Author-email: martino.pilia@gmail.com
Keywords: jacobian,displacement,image processing
Classifier: Programming Language :: Python :: 3
Classifier: License :: OSI Approved :: MIT License
Classifier: Operating System :: MacOS
Classifier: Operating System :: Microsoft :: Windows
Classifier: Operating System :: POSIX :: Linux
License-File: LICENSE
Requires-Dist: numpy>=1.15.1
Requires-Dist: scipy>=1.1.0
Requires-Dist: SimpleITK>=1.1.0
Provides-Extra: itk
Requires-Dist: itk>=4.12; extra == "itk"
Provides-Extra: ply
Requires-Dist: ply>=3.11; extra == "ply"
Provides-Extra: skimage
Requires-Dist: scikit-image>=0.14.1; extra == "skimage"
Provides-Extra: vtk
Requires-Dist: vtk>=7.0; extra == "vtk"
